giterm/__init__.py
giterm/_version.py
giterm/cursutils.py
giterm/exception.py
giterm/giterm.py
giterm/gui.py
giterm/observer.py
giterm/panel.py
giterm/panelmanager.py
giterm/patch.py
giterm/postponer.py
giterm/rungit.py
giterm/textutils.py
giterm/watch.py
giterm-0.7.0.dist-info/LICENSE
giterm-0.7.0.dist-info/METADATA
giterm-0.7.0.dist-info/WHEEL
giterm-0.7.0.dist-info/entry_points.txt
giterm-0.7.0.dist-info/top_level.txt
giterm-0.7.0.dist-info/RECORD
