Metadata-Version: 2.1
Name: giterm
Version: 0.7.0
Summary: A terminal-based GUI client for Git
Home-page: https://github.com/timlegrand/giterm
Download-URL: https://github.com/timlegrand/giterm
Author: Tim Legrand
Author-email: timlegrand.perso+dev@gmail.com
License: BSD 2-Clause
Keywords: git,client,terminal,console
Classifier: Development Status :: 5 - Production/Stable
Classifier: Environment :: Console :: Curses
Classifier: Intended Audience :: Developers
Classifier: License :: OSI Approved :: BSD License
Classifier: Operating System :: OS Independent
Classifier: Programming Language :: Python
Classifier: Programming Language :: Python :: 3
Classifier: Natural Language :: English
Classifier: Topic :: Software Development :: Version Control
License-File: LICENSE
Requires-Dist: watchdog (==2.2.1)
Requires-Dist: six (==1.10.0)
